{
  "uuid": "732d8e76-2edf-499e-872b-6b0efdacfc1a",
  "lastMigration": 24,
  "name": "Peanut Skills Test APi",
  "endpointPrefix": "",
  "latency": 0,
  "port": 3002,
  "hostname": "0.0.0.0",
  "routes": [
    {
      "uuid": "b8d0bda7-20d4-46cc-be95-4980c2909881",
      "documentation": "Accepts `page` as a param",
      "method": "get",
      "endpoint": "api/web/posts",
      "responses": [
        {
          "uuid": "fa7ffc10-b394-49d5-a9b6-af1cf563b877",
          "body": "{\n  \"pages\": [\n    {\n      \"published_at\": \"2023-05-09T10:11:00.000Z\",\n      \"heading\": \"1 Week Pregnant: What to Expect During Pregnancy\",\n      \"summary\": \"It’s like you’re both pregnant and not pregnant all at the same time\",\n      \"slug\": \"blog/1-week-pregnant\",\n      \"locale\": \"en\",\n      \"children\": [],\n      \"featured\": false,\n      \"i18n_pages\": [\n        [\n          \"es\",\n          \"blog/1-weeks-pregnant-es\"\n        ],\n        [\n          \"en\",\n          \"blog/1-week-pregnant\"\n        ]\n      ],\n      \"tag\": {\n        \"id\": 84,\n        \"name\": \"Pregnancy Week-by-Week\"\n      },\n      \"hero_image_url\": \"https://assets-production.teampeanut.com/stored-image/{width}/2hd4n-6w0zbu.jpg?ow=240&oh=240\",\n      \"author\": {\n        \"name\": \"Tassia Agatowski\",\n        \"avatar_url\": \"https://assets-production.teampeanut.com/stored-image/{width}/qpt3-m56abc.jpg?ow=1781&oh=1780\"\n      }\n    },\n    {\n      \"published_at\": \"2023-05-02T14:10:35.522Z\",\n      \"heading\": \"2 Weeks Pregnant? What to Expect During Pregnancy\",\n      \"summary\": \"2 weeks pregnant is... *drum roll please*... ovulation time!\",\n      \"slug\": \"blog/2-weeks-pregnant\",\n      \"locale\": \"en\",\n      \"children\": [],\n      \"featured\": false,\n      \"i18n_pages\": [\n        [\n          \"es\",\n          \"blog/2-semanas-de-embarazo\"\n        ],\n        [\n          \"en\",\n          \"blog/2-weeks-pregnant\"\n        ]\n      ],\n      \"tag\": {\n        \"id\": 84,\n        \"name\": \"Pregnancy Week-by-Week\"\n      },\n      \"hero_image_url\": \"https://assets-production.teampeanut.com/stored-image/{width}/2hd4r-2nivnj.jpg?ow=240&oh=240\",\n      \"author\": {\n        \"name\": \"Tassia Agatowski\",\n        \"avatar_url\": \"https://assets-production.teampeanut.com/stored-image/{width}/r27q-317c54.jpg?ow=1781&oh=1780\"\n      }\n    },\n    {\n      \"published_at\": \"2023-05-09T10:09:00.000Z\",\n      \"heading\": \"3 Weeks Pregnant: Baby is as big as a vanilla bean seed!\",\n      \"summary\": \"What is even happening inside you? Let’s find out. \",\n      \"slug\": \"blog/3-weeks-pregnant\",\n      \"locale\": \"en\",\n      \"children\": [],\n      \"featured\": false,\n      \"i18n_pages\": [\n        [\n          \"es\",\n          \"blog/3-semanas-de-embarazo\"\n        ],\n        [\n          \"en\",\n          \"blog/3-weeks-pregnant\"\n        ]\n      ],\n      \"tag\": {\n        \"id\": 84,\n        \"name\": \"Pregnancy Week-by-Week\"\n      },\n      \"hero_image_url\": \"https://assets-production.teampeanut.com/stored-image/{width}/2hd4w-9yqzxx.jpg?ow=240&oh=240\",\n      \"author\": {\n        \"name\": \"Tassia Agatowski\",\n        \"avatar_url\": \"https://assets-production.teampeanut.com/stored-image/{width}/r670-7cvu6y.jpg?ow=1781&oh=1780\"\n      }\n    },\n    {\n      \"published_at\": \"2023-05-09T10:08:00.000Z\",\n      \"heading\": \"4 Weeks Pregnant: Baby is as big as a poppy seed!\",\n      \"summary\": \"At this point, your baby-to-be is about 0.2mm\",\n      \"slug\": \"blog/4-weeks-pregnant\",\n      \"locale\": \"en\",\n      \"children\": [],\n      \"featured\": false,\n      \"i18n_pages\": [\n        [\n          \"es\",\n          \"blog/4-semanas-de-embarazo\"\n        ],\n        [\n          \"en\",\n          \"blog/4-weeks-pregnant\"\n        ]\n      ],\n      \"tag\": {\n        \"id\": 84,\n        \"name\": \"Pregnancy Week-by-Week\"\n      },\n      \"hero_image_url\": \"https://assets-production.teampeanut.com/stored-image/{width}/2hd50-6b6204.jpg?ow=240&oh=240\",\n      \"author\": {\n        \"name\": \"Tassia Agatowski\",\n        \"avatar_url\": \"https://assets-production.teampeanut.com/stored-image/{width}/rd8u-u02kh5.jpg?ow=1781&oh=1780\"\n      }\n    },\n    {\n      \"published_at\": \"2023-05-09T10:07:00.000Z\",\n      \"heading\": \"5 Weeks Pregnant: Baby is as big as an apple seed!\",\n      \"summary\": \"Baby's just one-tenth the size of an aspirin.\",\n      \"slug\": \"blog/5-weeks-pregnant\",\n      \"locale\": \"en\",\n      \"children\": [],\n      \"featured\": false,\n      \"i18n_pages\": [\n        [\n          \"es\",\n          \"blog/5-semanas-de-embarazo\"\n        ],\n        [\n          \"en\",\n          \"blog/5-weeks-pregnant\"\n        ]\n      ],\n      \"tag\": {\n        \"id\": 84,\n        \"name\": \"Pregnancy Week-by-Week\"\n      },\n      \"hero_image_url\": \"https://assets-production.teampeanut.com/stored-image/{width}/2hd51-bkcsrg.jpg?ow=240&oh=240\",\n      \"author\": {\n        \"name\": \"Tassia Agatowski\",\n        \"avatar_url\": \"https://assets-production.teampeanut.com/stored-image/{width}/sfam-7od57b.jpg?ow=1781&oh=1780\"\n      }\n    },\n    {\n      \"published_at\": \"2023-05-09T10:06:00.000Z\",\n      \"heading\": \"6 Weeks Pregnant: Baby is as big as a sweet pea!\",\n      \"summary\": \"There are some truly mind-blowing things happening inside you.\",\n      \"slug\": \"blog/6-weeks-pregnant\",\n      \"locale\": \"en\",\n      \"children\": [],\n      \"featured\": false,\n      \"i18n_pages\": [\n        [\n          \"es\",\n          \"blog/6-semanas-de-embarazo\"\n        ],\n        [\n          \"en\",\n          \"blog/6-weeks-pregnant\"\n        ]\n      ],\n      \"tag\": {\n        \"id\": 84,\n        \"name\": \"Pregnancy Week-by-Week\"\n      },\n      \"hero_image_url\": \"https://assets-production.teampeanut.com/stored-image/{width}/2hd52-rqcga7.jpg?ow=240&oh=240\",\n      \"author\": {\n        \"name\": \"Tassia Agatowski\",\n        \"avatar_url\": \"https://assets-production.teampeanut.com/stored-image/{width}/sh8d-1q3mb8.jpg?ow=1781&oh=1780\"\n      }\n    },\n    {\n      \"published_at\": \"2023-05-09T10:05:00.000Z\",\n      \"heading\": \"7 Weeks Pregnant: Baby is as big as a blueberry!\",\n      \"summary\": \"Your little peanut has just doubled in size from last week.\",\n      \"slug\": \"blog/7-weeks-pregnant\",\n      \"locale\": \"en\",\n      \"children\": [],\n      \"featured\": false,\n      \"i18n_pages\": [\n        [\n          \"es\",\n          \"blog/7-semanas-de-embarazo\"\n        ],\n        [\n          \"en\",\n          \"blog/7-weeks-pregnant\"\n        ]\n      ],\n      \"tag\": {\n        \"id\": 84,\n        \"name\": \"Pregnancy Week-by-Week\"\n      },\n      \"hero_image_url\": \"https://assets-production.teampeanut.com/stored-image/{width}/2hd54-u5senf.jpg?ow=240&oh=240\",\n      \"author\": {\n        \"name\": \"Tassia Agatowski\",\n        \"avatar_url\": \"https://assets-production.teampeanut.com/stored-image/{width}/t251-3ffo0v.jpg?ow=1781&oh=1780\"\n      }\n    },\n    {\n      \"published_at\": \"2023-05-09T10:04:00.000Z\",\n      \"heading\": \"8 Weeks Pregnant: Baby is as big as a peanut!\",\n      \"summary\": \"Your baby-to-be is officially about the size of a peanut.\",\n      \"slug\": \"blog/8-weeks-pregnant\",\n      \"locale\": \"en\",\n      \"children\": [],\n      \"featured\": false,\n      \"i18n_pages\": [\n        [\n          \"es\",\n          \"blog/8-semanas-de-embarazo\"\n        ],\n        [\n          \"en\",\n          \"blog/8-weeks-pregnant\"\n        ]\n      ],\n      \"tag\": {\n        \"id\": 84,\n        \"name\": \"Pregnancy Week-by-Week\"\n      },\n      \"hero_image_url\": \"https://assets-production.teampeanut.com/stored-image/{width}/2hd4g-6oljml.jpg?ow=240&oh=240\",\n      \"author\": {\n        \"name\": \"Tassia Agatowski\",\n        \"avatar_url\": \"https://assets-production.teampeanut.com/stored-image/{width}/uxkz-bylc4f.jpg?ow=1781&oh=1780\"\n      }\n    },\n    {\n      \"published_at\": \"2023-05-09T10:03:00.000Z\",\n      \"heading\": \"9 Weeks Pregnant: Baby is as big as a cherry!\",\n      \"summary\": \"Your little one is coming in at approximately 0.9 inches.\",\n      \"slug\": \"blog/9-weeks-pregnant\",\n      \"locale\": \"en\",\n      \"children\": [],\n      \"featured\": false,\n      \"i18n_pages\": [\n        [\n          \"es\",\n          \"blog/9-semanas-de-embarazo\"\n        ],\n        [\n          \"en\",\n          \"blog/9-weeks-pregnant\"\n        ]\n      ],\n      \"tag\": {\n        \"id\": 84,\n        \"name\": \"Pregnancy Week-by-Week\"\n      },\n      \"hero_image_url\": \"https://assets-production.teampeanut.com/stored-image/{width}/2hd58-qvh566.jpg?ow=240&oh=240\",\n      \"author\": {\n        \"name\": \"Tassia Agatowski\",\n        \"avatar_url\": \"https://assets-production.teampeanut.com/stored-image/{width}/sfj8-1of9cw.jpg?ow=1781&oh=1780\"\n      }\n    },\n    {\n      \"published_at\": \"2023-05-09T10:02:00.000Z\",\n      \"heading\": \"10 Weeks Pregnant: Baby is as big as a strawberry!\",\n      \"summary\": \"Baby is now about 1.25 inches, cute!\",\n      \"slug\": \"blog/10-weeks-pregnant\",\n      \"locale\": \"en\",\n      \"children\": [],\n      \"featured\": false,\n      \"i18n_pages\": [\n        [\n          \"es\",\n          \"blog/10-semanas-de-embarazo\"\n        ],\n        [\n          \"en\",\n          \"blog/10-weeks-pregnant\"\n        ]\n      ],\n      \"tag\": {\n        \"id\": 84,\n        \"name\": \"Pregnancy Week-by-Week\"\n      },\n      \"hero_image_url\": \"https://assets-production.teampeanut.com/stored-image/{width}/2hgb4-se6ixn.jpg?ow=240&oh=240\",\n      \"author\": {\n        \"name\": \"Tassia Agatowski\",\n        \"avatar_url\": \"https://assets-production.teampeanut.com/stored-image/{width}/sf71-gsa6og.jpg?ow=1781&oh=1780\"\n      }\n    },\n    {\n      \"published_at\": \"2023-05-09T10:01:00.000Z\",\n      \"heading\": \"11 Weeks Pregnant: Baby is as big as a lime!\",\n      \"summary\": \"You’re over a quarter of the way through. Woah!\",\n      \"slug\": \"blog/11-weeks-pregnant\",\n      \"locale\": \"en\",\n      \"children\": [],\n      \"featured\": false,\n      \"i18n_pages\": [\n        [\n          \"es\",\n          \"blog/11-semanas-de-embarazo\"\n        ],\n        [\n          \"en\",\n          \"blog/11-weeks-pregnant\"\n        ]\n      ],\n      \"tag\": {\n        \"id\": 84,\n        \"name\": \"Pregnancy Week-by-Week\"\n      },\n      \"hero_image_url\": \"https://assets-production.teampeanut.com/stored-image/{width}/2hd73-aguf3r.jpg?ow=240&oh=240\",\n      \"author\": {\n        \"name\": \"Tassia Agatowski\",\n        \"avatar_url\": \"https://assets-production.teampeanut.com/stored-image/{width}/vumd-x4yhp7.jpg?ow=1781&oh=1780\"\n      }\n    },\n    {\n      \"published_at\": \"2023-05-02T14:00:35.552Z\",\n      \"heading\": \"12 Weeks Pregnant: Baby is as big as a plum!\",\n      \"summary\": \"You’re in the third month of your pregnancy!\",\n      \"slug\": \"blog/12-weeks-pregnant\",\n      \"locale\": \"en\",\n      \"children\": [],\n      \"featured\": false,\n      \"i18n_pages\": [\n        [\n          \"es\",\n          \"blog/12-semanas-de-embarazo\"\n        ],\n        [\n          \"en\",\n          \"blog/12-weeks-pregnant\"\n        ]\n      ],\n      \"tag\": {\n        \"id\": 84,\n        \"name\": \"Pregnancy Week-by-Week\"\n      },\n      \"hero_image_url\": \"https://assets-production.teampeanut.com/stored-image/{width}/2hd7j-q1dali.jpg?ow=240&oh=240\",\n      \"author\": {\n        \"name\": \"Tassia Agatowski\",\n        \"avatar_url\": \"https://assets-production.teampeanut.com/stored-image/{width}/rgsi-zepu5m.jpg?ow=1781&oh=1780\"\n      }\n    },\n    {\n      \"published_at\": \"2023-05-09T11:59:00.000Z\",\n      \"heading\": \"13 Weeks Pregnant: Baby is as big as a lemon!\",\n      \"summary\": \"Into your third month of pregnancy.\",\n      \"slug\": \"blog/13-weeks-pregnant\",\n      \"locale\": \"en\",\n      \"children\": [],\n      \"featured\": false,\n      \"i18n_pages\": [\n        [\n          \"es\",\n          \"blog/13-semanas-de-embarazo\"\n        ],\n        [\n          \"en\",\n          \"blog/13-weeks-pregnant\"\n        ]\n      ],\n      \"tag\": {\n        \"id\": 84,\n        \"name\": \"Pregnancy Week-by-Week\"\n      },\n      \"hero_image_url\": \"https://assets-production.teampeanut.com/stored-image/{width}/2hd7o-cf5x8.jpg?ow=240&oh=240\",\n      \"author\": {\n        \"name\": \"Tassia Agatowski\",\n        \"avatar_url\": \"https://assets-production.teampeanut.com/stored-image/{width}/zkqz-klsiaa.jpg?ow=1781&oh=1780\"\n      }\n    },\n    {\n      \"published_at\": \"2023-05-09T11:58:00.000Z\",\n      \"heading\": \"14 Weeks Pregnant: Baby is as big as a peach!\",\n      \"summary\": \"Welcome to the second trimester!\",\n      \"slug\": \"blog/14-weeks-pregnant\",\n      \"locale\": \"en\",\n      \"children\": [],\n      \"featured\": false,\n      \"i18n_pages\": [\n        [\n          \"es\",\n          \"blog/14-semanas-de-embarazo\"\n        ],\n        [\n          \"en\",\n          \"blog/14-weeks-pregnant\"\n        ]\n      ],\n      \"tag\": {\n        \"id\": 84,\n        \"name\": \"Pregnancy Week-by-Week\"\n      },\n      \"hero_image_url\": \"https://assets-production.teampeanut.com/stored-image/{width}/2hd7u-22nkl5.jpg?ow=240&oh=240\",\n      \"author\": {\n        \"name\": \"Tassia Agatowski\",\n        \"avatar_url\": \"https://assets-production.teampeanut.com/stored-image/{width}/zcfj-848e2y.jpg?ow=1781&oh=1780\"\n      }\n    }\n  ],\n  \"last_page\": false,\n  \"tags\": [\n    {\n      \"id\": 56,\n      \"name\": \"Baby\",\n      \"title\": null,\n      \"meta_description\": null\n    },\n    {\n      \"id\": 82,\n      \"name\": \"Baby care\",\n      \"title\": null,\n      \"meta_description\": null\n    },\n    {\n      \"id\": 73,\n      \"name\": \"Baby Care\",\n      \"title\": null,\n      \"meta_description\": null\n    },\n    {\n      \"id\": 63,\n      \"name\": \"Baby Feeding\",\n      \"title\": null,\n      \"meta_description\": null\n    },\n    {\n      \"id\": 77,\n      \"name\": \"Baby names\",\n      \"title\": null,\n      \"meta_description\": null\n    },\n    {\n      \"id\": 52,\n      \"name\": \"Baby Names\",\n      \"title\": null,\n      \"meta_description\": null\n    },\n    {\n      \"id\": 86,\n      \"name\": \"Baby Products\",\n      \"title\": null,\n      \"meta_description\": null\n    },\n    {\n      \"id\": 66,\n      \"name\": \"Baby Showers\",\n      \"title\": null,\n      \"meta_description\": null\n    },\n    {\n      \"id\": 72,\n      \"name\": \"Baby sleep\",\n      \"title\": null,\n      \"meta_description\": null\n    },\n    {\n      \"id\": 67,\n      \"name\": \"Baby Sleep\",\n      \"title\": null,\n      \"meta_description\": null\n    },\n    {\n      \"id\": 59,\n      \"name\": \"Beauty\",\n      \"title\": null,\n      \"meta_description\": null\n    },\n    {\n      \"id\": 69,\n      \"name\": \"Birth\",\n      \"title\": null,\n      \"meta_description\": null\n    },\n    {\n      \"id\": 62,\n      \"name\": \"Breastfeeding\",\n      \"title\": null,\n      \"meta_description\": null\n    },\n    {\n      \"id\": 43,\n      \"name\": \"Children's Activities\",\n      \"title\": null,\n      \"meta_description\": null\n    },\n    {\n      \"id\": 76,\n      \"name\": \"Family\",\n      \"title\": null,\n      \"meta_description\": null\n    },\n    {\n      \"id\": 37,\n      \"name\": \"Fertility\",\n      \"title\": null,\n      \"meta_description\": null\n    },\n    {\n      \"id\": 68,\n      \"name\": \"From Peanut\",\n      \"title\": null,\n      \"meta_description\": null\n    },\n    {\n      \"id\": 50,\n      \"name\": \"Labor\",\n      \"title\": null,\n      \"meta_description\": null\n    },\n    {\n      \"id\": 92,\n      \"name\": \"LGBTQIA+\",\n      \"title\": null,\n      \"meta_description\": null\n    },\n    {\n      \"id\": 14,\n      \"name\": \"Lifestyle\",\n      \"title\": null,\n      \"meta_description\": null\n    },\n    {\n      \"id\": 23,\n      \"name\": \"Menopause\",\n      \"title\": null,\n      \"meta_description\": null\n    },\n    {\n      \"id\": 75,\n      \"name\": \"Mental health\",\n      \"title\": null,\n      \"meta_description\": null\n    },\n    {\n      \"id\": 60,\n      \"name\": \"Mental Health\",\n      \"title\": null,\n      \"meta_description\": null\n    },\n    {\n      \"id\": 3,\n      \"name\": \"Motherhood\",\n      \"title\": \"Motherhood - Tips & Advice from Peanut\",\n      \"meta_description\": \"Everything you need to know about motherhood. Expert articles, development guides, parenting tips, and so much more.\"\n    },\n    {\n      \"id\": 55,\n      \"name\": \"Newborn\",\n      \"title\": null,\n      \"meta_description\": null\n    },\n    {\n      \"id\": 49,\n      \"name\": \"Parenthood\",\n      \"title\": null,\n      \"meta_description\": null\n    },\n    {\n      \"id\": 45,\n      \"name\": \"Parenting\",\n      \"title\": null,\n      \"meta_description\": null\n    },\n    {\n      \"id\": 5,\n      \"name\": \"Peanut News\",\n      \"title\": \"Peanut - App News & Updates\",\n      \"meta_description\": \"Everything you need to know about the Peanut app. Feature updates, app news, and handy how-tos.\"\n    },\n    {\n      \"id\": 61,\n      \"name\": \"Postpartum\",\n      \"title\": null,\n      \"meta_description\": null\n    },\n    {\n      \"id\": 2,\n      \"name\": \"Pregnancy\",\n      \"title\": \"Pregnancy - Tips & Advice from Peanut\",\n      \"meta_description\": \"Everything you need to know about pregnancy. Expert articles, week-by-week guides, baby name inspiration, and so much more. \"\n    },\n    {\n      \"id\": 57,\n      \"name\": \"Pregnancy Announcements\",\n      \"title\": null,\n      \"meta_description\": null\n    },\n    {\n      \"id\": 58,\n      \"name\": \"Pregnancy Care\",\n      \"title\": null,\n      \"meta_description\": null\n    },\n    {\n      \"id\": 54,\n      \"name\": \"Pregnancy Loss\",\n      \"title\": null,\n      \"meta_description\": null\n    },\n    {\n      \"id\": 78,\n      \"name\": \"Pregnancy nutrition\",\n      \"title\": null,\n      \"meta_description\": null\n    },\n    {\n      \"id\": 83,\n      \"name\": \"Pregnancy Nutrition\",\n      \"title\": null,\n      \"meta_description\": null\n    },\n    {\n      \"id\": 89,\n      \"name\": \"Pregnancy Scans\",\n      \"title\": null,\n      \"meta_description\": null\n    },\n    {\n      \"id\": 79,\n      \"name\": \"Pregnancy symptoms\",\n      \"title\": null,\n      \"meta_description\": null\n    },\n    {\n      \"id\": 64,\n      \"name\": \"Pregnancy Symptoms\",\n      \"title\": null,\n      \"meta_description\": null\n    },\n    {\n      \"id\": 74,\n      \"name\": \"Pregnancy tests\",\n      \"title\": null,\n      \"meta_description\": null\n    },\n    {\n      \"id\": 53,\n      \"name\": \"Pregnancy Tests\",\n      \"title\": null,\n      \"meta_description\": null\n    },\n    {\n      \"id\": 84,\n      \"name\": \"Pregnancy Week-by-Week\",\n      \"title\": null,\n      \"meta_description\": null\n    },\n    {\n      \"id\": 85,\n      \"name\": \"Pregnancy Weeky-by-Week\",\n      \"title\": null,\n      \"meta_description\": null\n    },\n    {\n      \"id\": 70,\n      \"name\": \"Pumping\",\n      \"title\": null,\n      \"meta_description\": null\n    },\n    {\n      \"id\": 88,\n      \"name\": \"Shopping\",\n      \"title\": null,\n      \"meta_description\": null\n    },\n    {\n      \"id\": 80,\n      \"name\": \"Teething\",\n      \"title\": null,\n      \"meta_description\": null\n    },\n    {\n      \"id\": 81,\n      \"name\": \"Toddler\",\n      \"title\": null,\n      \"meta_description\": null\n    },\n    {\n      \"id\": 71,\n      \"name\": \"Trying for a baby\",\n      \"title\": null,\n      \"meta_description\": null\n    },\n    {\n      \"id\": 10,\n      \"name\": \"Trying to conceive\",\n      \"title\": null,\n      \"meta_description\": null\n    },\n    {\n      \"id\": 51,\n      \"name\": \"Women's Health\",\n      \"title\": null,\n      \"meta_description\": null\n    },\n    {\n      \"id\": 91,\n      \"name\": \"Work & Motherhood\",\n      \"title\": null,\n      \"meta_description\": null\n    }\n  ]\n}",
          "latency": 0,
          "statusCode": 200,
          "label": "",
          "headers": [],
          "bodyType": "INLINE",
          "filePath": "",
          "databucketID": "",
          "sendFileAsBody": false,
          "rules": [],
          "rulesOperator": "OR",
          "disableTemplating": false,
          "fallbackTo404": false,
          "default": true
        },
        {
          "uuid": "735ac6c9-7681-444f-98a7-e0a7f61b069a",
          "body": "{\n  \"pages\": [\n    {\n      \"published_at\": \"2023-05-09T10:57:00.000Z\",\n      \"heading\": \"15 Weeks Pregnant: Baby is as big as a navel orange!\",\n      \"summary\": \"Your little one is now about the size of the palm of your hand. \",\n      \"slug\": \"blog/15-weeks-pregnant\",\n      \"locale\": \"en\",\n      \"children\": [],\n      \"featured\": false,\n      \"i18n_pages\": [\n        [\n          \"es\",\n          \"blog/15-semanas-de-embarazo\"\n        ],\n        [\n          \"en\",\n          \"blog/15-weeks-pregnant\"\n        ]\n      ],\n      \"tag\": {\n        \"id\": 84,\n        \"name\": \"Pregnancy Week-by-Week\"\n      },\n      \"hero_image_url\": \"https://assets-production.teampeanut.com/stored-image/{width}/2hd7x-qqysco.jpg?ow=240&oh=240\",\n      \"author\": {\n        \"name\": \"Tassia Agatowski\",\n        \"avatar_url\": \"https://assets-production.teampeanut.com/stored-image/{width}/t28h-oog2jd.jpg?ow=1781&oh=1780\"\n      }\n    },\n    {\n      \"published_at\": \"2023-05-09T11:56:00.000Z\",\n      \"heading\": \"16 Weeks Pregnant: Baby is as big as an avocado!\",\n      \"summary\": \"Baby is now around 4.5inches long. About the same as an avocado.\",\n      \"slug\": \"blog/16-weeks-pregnant\",\n      \"locale\": \"en\",\n      \"children\": [],\n      \"featured\": false,\n      \"i18n_pages\": [\n        [\n          \"es\",\n          \"blog/16-semanas-de-embarazo\"\n        ],\n        [\n          \"en\",\n          \"blog/16-weeks-pregnant\"\n        ]\n      ],\n      \"tag\": {\n        \"id\": 84,\n        \"name\": \"Pregnancy Week-by-Week\"\n      },\n      \"hero_image_url\": \"https://assets-production.teampeanut.com/stored-image/{width}/2hd90-sy0oya.jpg?ow=240&oh=240\",\n      \"author\": {\n        \"name\": \"Tassia Agatowski\",\n        \"avatar_url\": \"https://assets-production.teampeanut.com/stored-image/{width}/tl6z-3nmo0o.jpg?ow=1781&oh=1780\"\n      }\n    },\n    {\n      \"published_at\": \"2023-05-09T11:55:00.000Z\",\n      \"heading\": \"17 Weeks Pregnant: Baby is as big as a pomegranate!\",\n      \"summary\": \"Your baby is now about the size of a pomegranate. Too cute!\",\n      \"slug\": \"blog/17-weeks-pregnant\",\n      \"locale\": \"en\",\n      \"children\": [],\n      \"featured\": false,\n      \"i18n_pages\": [\n        [\n          \"es\",\n          \"blog/17-semanas-de-embarazo\"\n        ],\n        [\n          \"en\",\n          \"blog/17-weeks-pregnant\"\n        ]\n      ],\n      \"tag\": {\n        \"id\": 84,\n        \"name\": \"Pregnancy Week-by-Week\"\n      },\n      \"hero_image_url\": \"https://assets-production.teampeanut.com/stored-image/{width}/2hd98-3ate1w.jpg?ow=240&oh=240\",\n      \"author\": {\n        \"name\": \"Tassia Agatowski\",\n        \"avatar_url\": \"https://assets-production.teampeanut.com/stored-image/{width}/t89s-e2j4j3.jpg?ow=1781&oh=1780\"\n      }\n    },\n    {\n      \"published_at\": \"2023-05-09T10:54:00.000Z\",\n      \"heading\": \"18 Weeks Pregnant: Baby is as big as an artichoke!\",\n      \"summary\": \"You're almost halfway through your pregnancy, mama!\",\n      \"slug\": \"blog/18-weeks-pregnant\",\n      \"locale\": \"en\",\n      \"children\": [],\n      \"featured\": false,\n      \"i18n_pages\": [\n        [\n          \"es\",\n          \"blog/18-semanas-de-embarazo\"\n        ],\n        [\n          \"en\",\n          \"blog/18-weeks-pregnant\"\n        ]\n      ],\n      \"tag\": {\n        \"id\": 84,\n        \"name\": \"Pregnancy Week-by-Week\"\n      },\n      \"hero_image_url\": \"https://assets-production.teampeanut.com/stored-image/{width}/2hd9h-c4b1uv.jpg?ow=240&oh=240\",\n      \"author\": {\n        \"name\": \"Tassia Agatowski\",\n        \"avatar_url\": \"https://assets-production.teampeanut.com/stored-image/{width}/strq-xh3z7s.jpg?ow=1781&oh=1780\"\n      }\n    },\n    {\n      \"published_at\": \"2023-05-09T10:53:00.000Z\",\n      \"heading\": \"19 Weeks Pregnant: Baby is as big as a mango!\",\n      \"summary\": \"Now that’s cause for celebration (with non-alcoholic bubbly, of course).\",\n      \"slug\": \"blog/19-weeks-pregnant\",\n      \"locale\": \"en\",\n      \"children\": [],\n      \"featured\": false,\n      \"i18n_pages\": [\n        [\n          \"es\",\n          \"blog/19-semanas-de-embarazo\"\n        ],\n        [\n          \"en\",\n          \"blog/19-weeks-pregnant\"\n        ]\n      ],\n      \"tag\": {\n        \"id\": 84,\n        \"name\": \"Pregnancy Week-by-Week\"\n      },\n      \"hero_image_url\": \"https://assets-production.teampeanut.com/stored-image/{width}/2hd9m-lbhc2e.jpg?ow=240&oh=240\",\n      \"author\": {\n        \"name\": \"Tassia Agatowski\",\n        \"avatar_url\": \"https://assets-production.teampeanut.com/stored-image/{width}/ujp7-zhpk59.jpg?ow=1781&oh=1780\"\n      }\n    },\n    {\n      \"published_at\": \"2023-05-09T10:52:00.000Z\",\n      \"heading\": \"20 Weeks Pregnant: Baby is as big as a banana!\",\n      \"summary\": \"Hello, little banana! 🍌\",\n      \"slug\": \"blog/20-weeks-pregnant\",\n      \"locale\": \"en\",\n      \"children\": [],\n      \"featured\": false,\n      \"i18n_pages\": [\n        [\n          \"es\",\n          \"blog/20-semanas-de-embarazo\"\n        ],\n        [\n          \"en\",\n          \"blog/20-weeks-pregnant\"\n        ]\n      ],\n      \"tag\": {\n        \"id\": 84,\n        \"name\": \"Pregnancy Week-by-Week\"\n      },\n      \"hero_image_url\": \"https://assets-production.teampeanut.com/stored-image/{width}/2hd9t-es6ejg.jpg?ow=240&oh=240\",\n      \"author\": {\n        \"name\": \"Tassia Agatowski\",\n        \"avatar_url\": \"https://assets-production.teampeanut.com/stored-image/{width}/rdt5-5tavb7.jpg?ow=1781&oh=1780\"\n      }\n    },\n    {\n      \"published_at\": \"2023-05-09T10:51:00.000Z\",\n      \"heading\": \"21 Weeks Pregnant: Baby is as big as an endive!\",\n      \"summary\": \"21 weeks pregnant is full of heart: heartbeats, heartburn, and heart-bursting kicks. \",\n      \"slug\": \"blog/21-weeks-pregnant\",\n      \"locale\": \"en\",\n      \"children\": [],\n      \"featured\": false,\n      \"i18n_pages\": [\n        [\n          \"es\",\n          \"blog/21-semanas-de-embarazo\"\n        ],\n        [\n          \"en\",\n          \"blog/21-weeks-pregnant\"\n        ]\n      ],\n      \"tag\": {\n        \"id\": 84,\n        \"name\": \"Pregnancy Week-by-Week\"\n      },\n      \"hero_image_url\": \"https://assets-production.teampeanut.com/stored-image/{width}/2hda7-t343g3.jpg?ow=240&oh=240\",\n      \"author\": {\n        \"name\": \"Tassia Agatowski\",\n        \"avatar_url\": \"https://assets-production.teampeanut.com/stored-image/{width}/vuqo-sd4jqm.jpg?ow=1781&oh=1780\"\n      }\n    },\n    {\n      \"published_at\": \"2023-05-09T11:50:00.000Z\",\n      \"heading\": \"22 Weeks Pregnant: Baby is as big as a coconut!\",\n      \"summary\": \"You’re not going to believe this, but you are past the halfway mark! \",\n      \"slug\": \"blog/22-weeks-pregnant\",\n      \"locale\": \"en\",\n      \"children\": [],\n      \"featured\": false,\n      \"i18n_pages\": [\n        [\n          \"es\",\n          \"blog/22-semanas-de-embarazo\"\n        ],\n        [\n          \"en\",\n          \"blog/22-weeks-pregnant\"\n        ]\n      ],\n      \"tag\": {\n        \"id\": 84,\n        \"name\": \"Pregnancy Week-by-Week\"\n      },\n      \"hero_image_url\": \"https://assets-production.teampeanut.com/stored-image/{width}/2hdae-fakikl.jpg?ow=240&oh=240\",\n      \"author\": {\n        \"name\": \"Tassia Agatowski\",\n        \"avatar_url\": \"https://assets-production.teampeanut.com/stored-image/{width}/uxx8-kojohl.jpg?ow=1781&oh=1780\"\n      }\n    },\n    {\n      \"published_at\": \"2023-05-09T11:49:00.000Z\",\n      \"heading\": \"23 Weeks Pregnant: Baby is as big as a grapefruit!\",\n      \"summary\": \"The third trimester is knocking at your door.\",\n      \"slug\": \"blog/23-weeks-pregnant\",\n      \"locale\": \"en\",\n      \"children\": [],\n      \"featured\": false,\n      \"i18n_pages\": [\n        [\n          \"es\",\n          \"blog/23-semanas-de-embarazo\"\n        ],\n        [\n          \"en\",\n          \"blog/23-weeks-pregnant\"\n        ]\n      ],\n      \"tag\": {\n        \"id\": 84,\n        \"name\": \"Pregnancy Week-by-Week\"\n      },\n      \"hero_image_url\": \"https://assets-production.teampeanut.com/stored-image/{width}/2hdak-u8ksqu.jpg?ow=240&oh=240\",\n      \"author\": {\n        \"name\": \"Tassia Agatowski\",\n        \"avatar_url\": \"https://assets-production.teampeanut.com/stored-image/{width}/zck3-d0wcy5.jpg?ow=1781&oh=1780\"\n      }\n    },\n    {\n      \"published_at\": \"2023-05-09T10:48:00.000Z\",\n      \"heading\": \"24 Weeks Pregnant: Baby is as big as a cantaloupe!\",\n      \"summary\": \"The third trimester is on its way.\",\n      \"slug\": \"blog/24-weeks-pregnant\",\n      \"locale\": \"en\",\n      \"children\": [],\n      \"featured\": false,\n      \"i18n_pages\": [\n        [\n          \"es\",\n          \"blog/24-semanas-de-embarazo\"\n        ],\n        [\n          \"en\",\n          \"blog/24-weeks-pregnant\"\n        ]\n      ],\n      \"tag\": {\n        \"id\": 84,\n        \"name\": \"Pregnancy Week-by-Week\"\n      },\n      \"hero_image_url\": \"https://assets-production.teampeanut.com/stored-image/{width}/2hdas-aiczwi.jpg?ow=240&oh=240\",\n      \"author\": {\n        \"name\": \"Tassia Agatowski\",\n        \"avatar_url\": \"https://assets-production.teampeanut.com/stored-image/{width}/z61v-obe2np.jpg?ow=1781&oh=1780\"\n      }\n    },\n    {\n      \"published_at\": \"2023-05-02T13:47:35.589Z\",\n      \"heading\": \"25 Weeks Pregnant: Baby is as big as a cauliflower!\",\n      \"summary\": \"Baby is now approximately the size of an eggplant.\",\n      \"slug\": \"blog/25-weeks-pregnant\",\n      \"locale\": \"en\",\n      \"children\": [],\n      \"featured\": false,\n      \"i18n_pages\": [\n        [\n          \"es\",\n          \"blog/25-semanas-de-embarazo\"\n        ],\n        [\n          \"en\",\n          \"blog/25-weeks-pregnant\"\n        ]\n      ],\n      \"tag\": {\n        \"id\": 84,\n        \"name\": \"Pregnancy Week-by-Week\"\n      },\n      \"hero_image_url\": \"https://assets-production.teampeanut.com/stored-image/{width}/2hdk8-3ttn6x.jpg?ow=240&oh=240\",\n      \"author\": {\n        \"name\": \"Tassia Agatowski\",\n        \"avatar_url\": \"https://assets-production.teampeanut.com/stored-image/{width}/sf93-mfvzrv.jpg?ow=1781&oh=1780\"\n      }\n    },\n    {\n      \"published_at\": \"2023-05-02T13:46:35.593Z\",\n      \"heading\": \"26 Weeks Pregnant: Baby is as big as a piece of kale!\",\n      \"summary\": \"14 weeks to go until your due date!\",\n      \"slug\": \"blog/26-weeks-pregnant\",\n      \"locale\": \"en\",\n      \"children\": [],\n      \"featured\": false,\n      \"i18n_pages\": [\n        [\n          \"es\",\n          \"blog/26-semanas-de-embarazo\"\n        ],\n        [\n          \"en\",\n          \"blog/26-weeks-pregnant\"\n        ]\n      ],\n      \"tag\": {\n        \"id\": 84,\n        \"name\": \"Pregnancy Week-by-Week\"\n      },\n      \"hero_image_url\": \"https://assets-production.teampeanut.com/stored-image/{width}/2hdkd-njiqyq.jpg?ow=240&oh=240\",\n      \"author\": {\n        \"name\": \"Tassia Agatowski\",\n        \"avatar_url\": \"https://assets-production.teampeanut.com/stored-image/{width}/sf60-rwbrq4.jpg?ow=1781&oh=1780\"\n      }\n    },\n    {\n      \"published_at\": \"2023-05-02T13:45:35.598Z\",\n      \"heading\": \"27 Weeks Pregnant: Baby is as big as a head of lettuce!\",\n      \"summary\": \"Goodbye, second trimester!\",\n      \"slug\": \"blog/27-weeks-pregnant\",\n      \"locale\": \"en\",\n      \"children\": [],\n      \"featured\": false,\n      \"i18n_pages\": [\n        [\n          \"es\",\n          \"blog/27-semanas-de-embarazo\"\n        ],\n        [\n          \"en\",\n          \"blog/27-weeks-pregnant\"\n        ]\n      ],\n      \"tag\": {\n        \"id\": 84,\n        \"name\": \"Pregnancy Week-by-Week\"\n      },\n      \"hero_image_url\": \"https://assets-production.teampeanut.com/stored-image/{width}/2hdkj-wxt4ng.jpg?ow=240&oh=240\",\n      \"author\": {\n        \"name\": \"Tassia Agatowski\",\n        \"avatar_url\": \"https://assets-production.teampeanut.com/stored-image/{width}/xw8d-wr0znc.jpg?ow=1781&oh=1780\"\n      }\n    },\n    {\n      \"published_at\": \"2023-05-02T13:44:35.601Z\",\n      \"heading\": \"28 Weeks Pregnant: Baby is as big as an eggplant!\",\n      \"summary\": \"Hello, third trimester!\",\n      \"slug\": \"blog/28-weeks-pregnant\",\n      \"locale\": \"en\",\n      \"children\": [],\n      \"featured\": false,\n      \"i18n_pages\": [\n        [\n          \"es\",\n          \"blog/28-semanas-de-embarazo\"\n        ],\n        [\n          \"en\",\n          \"blog/28-weeks-pregnant\"\n        ]\n      ],\n      \"tag\": {\n        \"id\": 84,\n        \"name\": \"Pregnancy Week-by-Week\"\n      },\n      \"hero_image_url\": \"https://assets-production.teampeanut.com/stored-image/{width}/2hdkn-jop90o.jpg?ow=240&oh=240\",\n      \"author\": {\n        \"name\": \"Tassia Agatowski\",\n        \"avatar_url\": \"https://assets-production.teampeanut.com/stored-image/{width}/vuui-8i42uy.jpg?ow=1781&oh=1780\"\n      }\n    }\n  ],\n  \"last_page\": false,\n  \"tags\": [\n    {\n      \"id\": 56,\n      \"name\": \"Baby\",\n      \"title\": null,\n      \"meta_description\": null\n    },\n    {\n      \"id\": 82,\n      \"name\": \"Baby care\",\n      \"title\": null,\n      \"meta_description\": null\n    },\n    {\n      \"id\": 73,\n      \"name\": \"Baby Care\",\n      \"title\": null,\n      \"meta_description\": null\n    },\n    {\n      \"id\": 63,\n      \"name\": \"Baby Feeding\",\n      \"title\": null,\n      \"meta_description\": null\n    },\n    {\n      \"id\": 77,\n      \"name\": \"Baby names\",\n      \"title\": null,\n      \"meta_description\": null\n    },\n    {\n      \"id\": 52,\n      \"name\": \"Baby Names\",\n      \"title\": null,\n      \"meta_description\": null\n    },\n    {\n      \"id\": 86,\n      \"name\": \"Baby Products\",\n      \"title\": null,\n      \"meta_description\": null\n    },\n    {\n      \"id\": 66,\n      \"name\": \"Baby Showers\",\n      \"title\": null,\n      \"meta_description\": null\n    },\n    {\n      \"id\": 72,\n      \"name\": \"Baby sleep\",\n      \"title\": null,\n      \"meta_description\": null\n    },\n    {\n      \"id\": 67,\n      \"name\": \"Baby Sleep\",\n      \"title\": null,\n      \"meta_description\": null\n    },\n    {\n      \"id\": 59,\n      \"name\": \"Beauty\",\n      \"title\": null,\n      \"meta_description\": null\n    },\n    {\n      \"id\": 69,\n      \"name\": \"Birth\",\n      \"title\": null,\n      \"meta_description\": null\n    },\n    {\n      \"id\": 62,\n      \"name\": \"Breastfeeding\",\n      \"title\": null,\n      \"meta_description\": null\n    },\n    {\n      \"id\": 43,\n      \"name\": \"Children's Activities\",\n      \"title\": null,\n      \"meta_description\": null\n    },\n    {\n      \"id\": 76,\n      \"name\": \"Family\",\n      \"title\": null,\n      \"meta_description\": null\n    },\n    {\n      \"id\": 37,\n      \"name\": \"Fertility\",\n      \"title\": null,\n      \"meta_description\": null\n    },\n    {\n      \"id\": 68,\n      \"name\": \"From Peanut\",\n      \"title\": null,\n      \"meta_description\": null\n    },\n    {\n      \"id\": 50,\n      \"name\": \"Labor\",\n      \"title\": null,\n      \"meta_description\": null\n    },\n    {\n      \"id\": 92,\n      \"name\": \"LGBTQIA+\",\n      \"title\": null,\n      \"meta_description\": null\n    },\n    {\n      \"id\": 14,\n      \"name\": \"Lifestyle\",\n      \"title\": null,\n      \"meta_description\": null\n    },\n    {\n      \"id\": 23,\n      \"name\": \"Menopause\",\n      \"title\": null,\n      \"meta_description\": null\n    },\n    {\n      \"id\": 75,\n      \"name\": \"Mental health\",\n      \"title\": null,\n      \"meta_description\": null\n    },\n    {\n      \"id\": 60,\n      \"name\": \"Mental Health\",\n      \"title\": null,\n      \"meta_description\": null\n    },\n    {\n      \"id\": 3,\n      \"name\": \"Motherhood\",\n      \"title\": \"Motherhood - Tips & Advice from Peanut\",\n      \"meta_description\": \"Everything you need to know about motherhood. Expert articles, development guides, parenting tips, and so much more.\"\n    },\n    {\n      \"id\": 55,\n      \"name\": \"Newborn\",\n      \"title\": null,\n      \"meta_description\": null\n    },\n    {\n      \"id\": 49,\n      \"name\": \"Parenthood\",\n      \"title\": null,\n      \"meta_description\": null\n    },\n    {\n      \"id\": 45,\n      \"name\": \"Parenting\",\n      \"title\": null,\n      \"meta_description\": null\n    },\n    {\n      \"id\": 5,\n      \"name\": \"Peanut News\",\n      \"title\": \"Peanut - App News & Updates\",\n      \"meta_description\": \"Everything you need to know about the Peanut app. Feature updates, app news, and handy how-tos.\"\n    },\n    {\n      \"id\": 61,\n      \"name\": \"Postpartum\",\n      \"title\": null,\n      \"meta_description\": null\n    },\n    {\n      \"id\": 2,\n      \"name\": \"Pregnancy\",\n      \"title\": \"Pregnancy - Tips & Advice from Peanut\",\n      \"meta_description\": \"Everything you need to know about pregnancy. Expert articles, week-by-week guides, baby name inspiration, and so much more. \"\n    },\n    {\n      \"id\": 57,\n      \"name\": \"Pregnancy Announcements\",\n      \"title\": null,\n      \"meta_description\": null\n    },\n    {\n      \"id\": 58,\n      \"name\": \"Pregnancy Care\",\n      \"title\": null,\n      \"meta_description\": null\n    },\n    {\n      \"id\": 54,\n      \"name\": \"Pregnancy Loss\",\n      \"title\": null,\n      \"meta_description\": null\n    },\n    {\n      \"id\": 78,\n      \"name\": \"Pregnancy nutrition\",\n      \"title\": null,\n      \"meta_description\": null\n    },\n    {\n      \"id\": 83,\n      \"name\": \"Pregnancy Nutrition\",\n      \"title\": null,\n      \"meta_description\": null\n    },\n    {\n      \"id\": 89,\n      \"name\": \"Pregnancy Scans\",\n      \"title\": null,\n      \"meta_description\": null\n    },\n    {\n      \"id\": 79,\n      \"name\": \"Pregnancy symptoms\",\n      \"title\": null,\n      \"meta_description\": null\n    },\n    {\n      \"id\": 64,\n      \"name\": \"Pregnancy Symptoms\",\n      \"title\": null,\n      \"meta_description\": null\n    },\n    {\n      \"id\": 74,\n      \"name\": \"Pregnancy tests\",\n      \"title\": null,\n      \"meta_description\": null\n    },\n    {\n      \"id\": 53,\n      \"name\": \"Pregnancy Tests\",\n      \"title\": null,\n      \"meta_description\": null\n    },\n    {\n      \"id\": 84,\n      \"name\": \"Pregnancy Week-by-Week\",\n      \"title\": null,\n      \"meta_description\": null\n    },\n    {\n      \"id\": 85,\n      \"name\": \"Pregnancy Weeky-by-Week\",\n      \"title\": null,\n      \"meta_description\": null\n    },\n    {\n      \"id\": 70,\n      \"name\": \"Pumping\",\n      \"title\": null,\n      \"meta_description\": null\n    },\n    {\n      \"id\": 88,\n      \"name\": \"Shopping\",\n      \"title\": null,\n      \"meta_description\": null\n    },\n    {\n      \"id\": 80,\n      \"name\": \"Teething\",\n      \"title\": null,\n      \"meta_description\": null\n    },\n    {\n      \"id\": 81,\n      \"name\": \"Toddler\",\n      \"title\": null,\n      \"meta_description\": null\n    },\n    {\n      \"id\": 71,\n      \"name\": \"Trying for a baby\",\n      \"title\": null,\n      \"meta_description\": null\n    },\n    {\n      \"id\": 10,\n      \"name\": \"Trying to conceive\",\n      \"title\": null,\n      \"meta_description\": null\n    },\n    {\n      \"id\": 51,\n      \"name\": \"Women's Health\",\n      \"title\": null,\n      \"meta_description\": null\n    },\n    {\n      \"id\": 91,\n      \"name\": \"Work & Motherhood\",\n      \"title\": null,\n      \"meta_description\": null\n    }\n  ]\n}",
          "latency": 0,
          "statusCode": 200,
          "label": "",
          "headers": [],
          "bodyType": "INLINE",
          "filePath": "",
          "databucketID": "",
          "sendFileAsBody": false,
          "rules": [
            {
              "target": "query",
              "modifier": "page",
              "value": "2",
              "invert": false,
              "operator": "equals"
            }
          ],
          "rulesOperator": "OR",
          "disableTemplating": false,
          "fallbackTo404": false,
          "default": false
        },
        {
          "uuid": "fca8a764-96c9-4d20-9bfe-e5598f44e2a0",
          "body": "{\n  \"pages\": [\n    {\n      \"published_at\": \"2023-05-02T13:43:35.604Z\",\n      \"heading\": \"29 Weeks Pregnant: Baby is as big as an acorn squash!\",\n      \"summary\": \"Baby’s the size of an acorn squash!\",\n      \"slug\": \"blog/29-weeks-pregnant\",\n      \"locale\": \"en\",\n      \"children\": [],\n      \"featured\": false,\n      \"i18n_pages\": [\n        [\n          \"es\",\n          \"blog/29-semanas-de-embarazo\"\n        ],\n        [\n          \"en\",\n          \"blog/29-weeks-pregnant\"\n        ]\n      ],\n      \"tag\": {\n        \"id\": 84,\n        \"name\": \"Pregnancy Week-by-Week\"\n      },\n      \"hero_image_url\": \"https://assets-production.teampeanut.com/stored-image/{width}/2hdky-l59kop.jpg?ow=240&oh=240\",\n      \"author\": {\n        \"name\": \"Tassia Agatowski\",\n        \"avatar_url\": \"https://assets-production.teampeanut.com/stored-image/{width}/wbk6-ul9h42.jpg?ow=1781&oh=1780\"\n      }\n    },\n    {\n      \"published_at\": \"2023-05-02T13:42:35.607Z\",\n      \"heading\": \"30 Weeks Pregnant: Baby is as big as a zucchini!\",\n      \"summary\": \"The home stretch is in sight!\",\n      \"slug\": \"blog/30-weeks-pregnant\",\n      \"locale\": \"en\",\n      \"children\": [],\n      \"featured\": false,\n      \"i18n_pages\": [\n        [\n          \"es\",\n          \"blog/30-semanas-de-embarazo\"\n        ],\n        [\n          \"en\",\n          \"blog/30-weeks-pregnant\"\n        ]\n      ],\n      \"tag\": {\n        \"id\": 84,\n        \"name\": \"Pregnancy Week-by-Week\"\n      },\n      \"hero_image_url\": \"https://assets-production.teampeanut.com/stored-image/{width}/2hdl7-5zckmy.jpg?ow=240&oh=240\",\n      \"author\": {\n        \"name\": \"Tassia Agatowski\",\n        \"avatar_url\": \"https://assets-production.teampeanut.com/stored-image/{width}/vxes-ctuk70.jpg?ow=1781&oh=1780\"\n      }\n    },\n    {\n      \"published_at\": \"2023-05-02T13:41:35.611Z\",\n      \"heading\": \"31 Weeks Pregnant: Baby is as big as a bunch of asparagus!\",\n      \"summary\": \"You're getting close to the big day!\",\n      \"slug\": \"blog/31-weeks-pregnant\",\n      \"locale\": \"en\",\n      \"children\": [],\n      \"featured\": false,\n      \"i18n_pages\": [\n        [\n          \"es\",\n          \"blog/31-semanas-de-embarazo\"\n        ],\n        [\n          \"en\",\n          \"blog/31-weeks-pregnant\"\n        ]\n      ],\n      \"tag\": {\n        \"id\": 84,\n        \"name\": \"Pregnancy Week-by-Week\"\n      },\n      \"hero_image_url\": \"https://assets-production.teampeanut.com/stored-image/{width}/2hdlc-hlkmt3.jpg?ow=240&oh=240\",\n      \"author\": {\n        \"name\": \"Tassia Agatowski\",\n        \"avatar_url\": \"https://assets-production.teampeanut.com/stored-image/{width}/vxbg-ce7aej.jpg?ow=1781&oh=1780\"\n      }\n    },\n    {\n      \"published_at\": \"2023-05-02T13:40:35.615Z\",\n      \"heading\": \"32 Weeks Pregnant: Baby is as big as a squash!\",\n      \"summary\": \"You're gearing up for your due date!\",\n      \"slug\": \"blog/32-weeks-pregnant\",\n      \"locale\": \"en\",\n      \"children\": [],\n      \"featured\": false,\n      \"i18n_pages\": [\n        [\n          \"es\",\n          \"blog/32-semanas-de-embarazo\"\n        ],\n        [\n          \"en\",\n          \"blog/32-weeks-pregnant\"\n        ]\n      ],\n      \"tag\": {\n        \"id\": 84,\n        \"name\": \"Pregnancy Week-by-Week\"\n      },\n      \"hero_image_url\": \"https://assets-production.teampeanut.com/stored-image/{width}/2hdlj-boffoc.jpg?ow=240&oh=240\",\n      \"author\": {\n        \"name\": \"Tassia Agatowski\",\n        \"avatar_url\": \"https://assets-production.teampeanut.com/stored-image/{width}/w26i-ggdnsg.jpg?ow=1781&oh=1780\"\n      }\n    },\n    {\n      \"published_at\": \"2023-05-02T13:39:35.619Z\",\n      \"heading\": \"33 Weeks Pregnant: Baby is as big as a stick of celery!\",\n      \"summary\": \"Only 7 weeks left!\",\n      \"slug\": \"blog/33-weeks-pregnant\",\n      \"locale\": \"en\",\n      \"children\": [],\n      \"featured\": false,\n      \"i18n_pages\": [\n        [\n          \"es\",\n          \"blog/33-semanas-de-embarazo\"\n        ],\n        [\n          \"en\",\n          \"blog/33-weeks-pregnant\"\n        ]\n      ],\n      \"tag\": {\n        \"id\": 84,\n        \"name\": \"Pregnancy Week-by-Week\"\n      },\n      \"hero_image_url\": \"https://assets-production.teampeanut.com/stored-image/{width}/2hdlq-vq3vqd.jpg?ow=240&oh=240\",\n      \"author\": {\n        \"name\": \"Tassia Agatowski\",\n        \"avatar_url\": \"https://assets-production.teampeanut.com/stored-image/{width}/xhih-s7o3td.jpg?ow=1781&oh=1780\"\n      }\n    },\n    {\n      \"published_at\": \"2023-05-02T13:38:35.622Z\",\n      \"heading\": \"34 Weeks Pregnant: Baby is as big as a butternut squash!\",\n      \"summary\": \"Baby is officially the size of a butternut squash.\",\n      \"slug\": \"blog/34-weeks-pregnant\",\n      \"locale\": \"en\",\n      \"children\": [],\n      \"featured\": false,\n      \"i18n_pages\": [\n        [\n          \"es\",\n          \"blog/34-semanas-de-embarazo\"\n        ],\n        [\n          \"en\",\n          \"blog/34-weeks-pregnant\"\n        ]\n      ],\n      \"tag\": {\n        \"id\": 85,\n        \"name\": \"Pregnancy Weeky-by-Week\"\n      },\n      \"hero_image_url\": \"https://assets-production.teampeanut.com/stored-image/{width}/2hdnj-emy254.jpg?ow=240&oh=240\",\n      \"author\": {\n        \"name\": \"Tassia Agatowski\",\n        \"avatar_url\": \"https://assets-production.teampeanut.com/stored-image/{width}/yb44-n3pf12.jpg?ow=1781&oh=1780\"\n      }\n    },\n    {\n      \"published_at\": \"2023-05-02T13:37:35.625Z\",\n      \"heading\": \"35 Weeks Pregnant: Baby is as big as a pineapple!\",\n      \"summary\": \"Baby is now the same size as a pineapple. Cute!\",\n      \"slug\": \"blog/35-weeks-pregnant\",\n      \"locale\": \"en\",\n      \"children\": [],\n      \"featured\": false,\n      \"i18n_pages\": [\n        [\n          \"es\",\n          \"blog/35-semanas-de-embarazo\"\n        ],\n        [\n          \"en\",\n          \"blog/35-weeks-pregnant\"\n        ]\n      ],\n      \"tag\": {\n        \"id\": 84,\n        \"name\": \"Pregnancy Week-by-Week\"\n      },\n      \"hero_image_url\": \"https://assets-production.teampeanut.com/stored-image/{width}/2hdnr-zbvyde.jpg?ow=240&oh=240\",\n      \"author\": {\n        \"name\": \"Tassia Agatowski\",\n        \"avatar_url\": \"https://assets-production.teampeanut.com/stored-image/{width}/uzhl-2h89vu.jpg?ow=1781&oh=1780\"\n      }\n    },\n    {\n      \"published_at\": \"2023-05-02T13:36:35.628Z\",\n      \"heading\": \"36 Weeks Pregnant: Baby is as big as a papaya!\",\n      \"summary\": \"Not long to go now.\",\n      \"slug\": \"blog/36-weeks-pregnant\",\n      \"locale\": \"en\",\n      \"children\": [],\n      \"featured\": false,\n      \"i18n_pages\": [\n        [\n          \"es\",\n          \"blog/36-semanas-de-embarazo\"\n        ],\n        [\n          \"en\",\n          \"blog/36-weeks-pregnant\"\n        ]\n      ],\n      \"tag\": {\n        \"id\": 84,\n        \"name\": \"Pregnancy Week-by-Week\"\n      },\n      \"hero_image_url\": \"https://assets-production.teampeanut.com/stored-image/{width}/2hdo1-erguw.jpg?ow=240&oh=240\",\n      \"author\": {\n        \"name\": \"Tassia Agatowski\",\n        \"avatar_url\": \"https://assets-production.teampeanut.com/stored-image/{width}/y82z-hd5864.jpg?ow=1781&oh=1780\"\n      }\n    },\n    {\n      \"published_at\": \"2023-05-02T13:35:35.631Z\",\n      \"heading\": \"37 Weeks Pregnant: Baby is as big as a Romaine lettuce!\",\n      \"summary\": \"Baby is about the size of a bunch of swiss chard!\",\n      \"slug\": \"blog/37-weeks-pregnant\",\n      \"locale\": \"en\",\n      \"children\": [],\n      \"featured\": false,\n      \"i18n_pages\": [\n        [\n          \"es\",\n          \"blog/37-semanas-de-embarazo\"\n        ],\n        [\n          \"en\",\n          \"blog/37-weeks-pregnant\"\n        ]\n      ],\n      \"tag\": {\n        \"id\": 84,\n        \"name\": \"Pregnancy Week-by-Week\"\n      },\n      \"hero_image_url\": \"https://assets-production.teampeanut.com/stored-image/{width}/2hdo5-w3tnlj.jpg?ow=240&oh=240\",\n      \"author\": {\n        \"name\": \"Tassia Agatowski\",\n        \"avatar_url\": \"https://assets-production.teampeanut.com/stored-image/{width}/uxtn-dooj7o.jpg?ow=1781&oh=1780\"\n      }\n    },\n    {\n      \"published_at\": \"2023-05-02T13:34:35.634Z\",\n      \"heading\": \"38 Weeks Pregnant: Baby is as big as a winter melon!\",\n      \"summary\": \"The finish line is very much in sight!\",\n      \"slug\": \"blog/38-weeks-pregnant\",\n      \"locale\": \"en\",\n      \"children\": [],\n      \"featured\": false,\n      \"i18n_pages\": [\n        [\n          \"es\",\n          \"blog/38-semanas-de-embarazo\"\n        ],\n        [\n          \"en\",\n          \"blog/38-weeks-pregnant\"\n        ]\n      ],\n      \"tag\": {\n        \"id\": 84,\n        \"name\": \"Pregnancy Week-by-Week\"\n      },\n      \"hero_image_url\": \"https://assets-production.teampeanut.com/stored-image/{width}/2hiui-s8stfo.jpg?ow=240&oh=240\",\n      \"author\": {\n        \"name\": \"Tassia Agatowski\",\n        \"avatar_url\": \"https://assets-production.teampeanut.com/stored-image/{width}/uxqw-285rz2.jpg?ow=1781&oh=1780\"\n      }\n    },\n    {\n      \"published_at\": \"2023-05-02T13:33:35.637Z\",\n      \"heading\": \"39 Weeks Pregnant: Baby is as big as a pumpkin!\",\n      \"summary\": \"At 39 weeks pregnant, you’re right on the cusp of mamahood.\",\n      \"slug\": \"blog/39-weeks-pregnant\",\n      \"locale\": \"en\",\n      \"children\": [],\n      \"featured\": false,\n      \"i18n_pages\": [\n        [\n          \"es\",\n          \"blog/39-semanas-de-embarazo\"\n        ],\n        [\n          \"en\",\n          \"blog/39-weeks-pregnant\"\n        ]\n      ],\n      \"tag\": {\n        \"id\": 84,\n        \"name\": \"Pregnancy Week-by-Week\"\n      },\n      \"hero_image_url\": \"https://assets-production.teampeanut.com/stored-image/{width}/2hdob-biir9h.jpg?ow=240&oh=240\",\n      \"author\": {\n        \"name\": \"Tassia Agatowski\",\n        \"avatar_url\": \"https://assets-production.teampeanut.com/stored-image/{width}/uxec-r611wz.jpg?ow=1781&oh=1780\"\n      }\n    },\n    {\n      \"published_at\": \"2023-05-02T13:32:35.641Z\",\n      \"heading\": \"40 Weeks Pregnant: Baby is as big as a watermelon!\",\n      \"summary\": \"Congratulations, soon-to-be-mama! You’re on the home stretch. \",\n      \"slug\": \"blog/40-weeks-pregnant\",\n      \"locale\": \"en\",\n      \"children\": [],\n      \"featured\": false,\n      \"i18n_pages\": [\n        [\n          \"es\",\n          \"blog/40-semanas-de-embarazo\"\n        ],\n        [\n          \"en\",\n          \"blog/40-weeks-pregnant\"\n        ]\n      ],\n      \"tag\": {\n        \"id\": 84,\n        \"name\": \"Pregnancy Week-by-Week\"\n      },\n      \"hero_image_url\": \"https://assets-production.teampeanut.com/stored-image/{width}/2hdog-wbv3gv.jpg?ow=240&oh=240\",\n      \"author\": {\n        \"name\": \"Tassia Agatowski\",\n        \"avatar_url\": \"https://assets-production.teampeanut.com/stored-image/{width}/qtep-b669g0.jpg?ow=178&oh=178\"\n      }\n    },\n    {\n      \"published_at\": \"2023-05-02T13:31:35.644Z\",\n      \"heading\": \"41 Weeks Pregnant: Baby is as big as a watermelon!\",\n      \"summary\": \"Your baby is getting ready to make an appearance!\",\n      \"slug\": \"blog/41-weeks-pregnant\",\n      \"locale\": \"en\",\n      \"children\": [],\n      \"featured\": false,\n      \"i18n_pages\": [\n        [\n          \"es\",\n          \"blog/41-semanas-de-embarazo\"\n        ],\n        [\n          \"en\",\n          \"blog/41-weeks-pregnant\"\n        ]\n      ],\n      \"tag\": {\n        \"id\": 84,\n        \"name\": \"Pregnancy Week-by-Week\"\n      },\n      \"hero_image_url\": \"https://assets-production.teampeanut.com/stored-image/{width}/2hdoo-mrs8st.jpg?ow=240&oh=240\",\n      \"author\": {\n        \"name\": \"Tassia Agatowski\",\n        \"avatar_url\": \"https://assets-production.teampeanut.com/stored-image/{width}/rr5l-y1pyiy.jpg?ow=1781&oh=1780\"\n      }\n    },\n    {\n      \"published_at\": \"2023-05-02T13:30:35.647Z\",\n      \"heading\": \"42 Weeks Pregnant: Baby is as big as a watermelon!\",\n      \"summary\": \"The finish line isn't too far in the distance. Hang in there!\",\n      \"slug\": \"blog/42-weeks-pregnant\",\n      \"locale\": \"en\",\n      \"children\": [],\n      \"featured\": false,\n      \"i18n_pages\": [\n        [\n          \"es\",\n          \"blog/42-semanas-de-embarazo\"\n        ],\n        [\n          \"en\",\n          \"blog/42-weeks-pregnant\"\n        ]\n      ],\n      \"tag\": {\n        \"id\": 84,\n        \"name\": \"Pregnancy Week-by-Week\"\n      },\n      \"hero_image_url\": \"https://assets-production.teampeanut.com/stored-image/{width}/2hdou-wzx82m.jpg?ow=240&oh=240\",\n      \"author\": {\n        \"name\": \"Tassia Agatowski\",\n        \"avatar_url\": \"https://assets-production.teampeanut.com/stored-image/{width}/rkdl-9682ca.jpg?ow=1781&oh=1780\"\n      }\n    }\n  ],\n  \"last_page\": false,\n  \"tags\": [\n    {\n      \"id\": 56,\n      \"name\": \"Baby\",\n      \"title\": null,\n      \"meta_description\": null\n    },\n    {\n      \"id\": 82,\n      \"name\": \"Baby care\",\n      \"title\": null,\n      \"meta_description\": null\n    },\n    {\n      \"id\": 73,\n      \"name\": \"Baby Care\",\n      \"title\": null,\n      \"meta_description\": null\n    },\n    {\n      \"id\": 63,\n      \"name\": \"Baby Feeding\",\n      \"title\": null,\n      \"meta_description\": null\n    },\n    {\n      \"id\": 77,\n      \"name\": \"Baby names\",\n      \"title\": null,\n      \"meta_description\": null\n    },\n    {\n      \"id\": 52,\n      \"name\": \"Baby Names\",\n      \"title\": null,\n      \"meta_description\": null\n    },\n    {\n      \"id\": 86,\n      \"name\": \"Baby Products\",\n      \"title\": null,\n      \"meta_description\": null\n    },\n    {\n      \"id\": 66,\n      \"name\": \"Baby Showers\",\n      \"title\": null,\n      \"meta_description\": null\n    },\n    {\n      \"id\": 72,\n      \"name\": \"Baby sleep\",\n      \"title\": null,\n      \"meta_description\": null\n    },\n    {\n      \"id\": 67,\n      \"name\": \"Baby Sleep\",\n      \"title\": null,\n      \"meta_description\": null\n    },\n    {\n      \"id\": 59,\n      \"name\": \"Beauty\",\n      \"title\": null,\n      \"meta_description\": null\n    },\n    {\n      \"id\": 69,\n      \"name\": \"Birth\",\n      \"title\": null,\n      \"meta_description\": null\n    },\n    {\n      \"id\": 62,\n      \"name\": \"Breastfeeding\",\n      \"title\": null,\n      \"meta_description\": null\n    },\n    {\n      \"id\": 43,\n      \"name\": \"Children's Activities\",\n      \"title\": null,\n      \"meta_description\": null\n    },\n    {\n      \"id\": 76,\n      \"name\": \"Family\",\n      \"title\": null,\n      \"meta_description\": null\n    },\n    {\n      \"id\": 37,\n      \"name\": \"Fertility\",\n      \"title\": null,\n      \"meta_description\": null\n    },\n    {\n      \"id\": 68,\n      \"name\": \"From Peanut\",\n      \"title\": null,\n      \"meta_description\": null\n    },\n    {\n      \"id\": 50,\n      \"name\": \"Labor\",\n      \"title\": null,\n      \"meta_description\": null\n    },\n    {\n      \"id\": 92,\n      \"name\": \"LGBTQIA+\",\n      \"title\": null,\n      \"meta_description\": null\n    },\n    {\n      \"id\": 14,\n      \"name\": \"Lifestyle\",\n      \"title\": null,\n      \"meta_description\": null\n    },\n    {\n      \"id\": 23,\n      \"name\": \"Menopause\",\n      \"title\": null,\n      \"meta_description\": null\n    },\n    {\n      \"id\": 75,\n      \"name\": \"Mental health\",\n      \"title\": null,\n      \"meta_description\": null\n    },\n    {\n      \"id\": 60,\n      \"name\": \"Mental Health\",\n      \"title\": null,\n      \"meta_description\": null\n    },\n    {\n      \"id\": 3,\n      \"name\": \"Motherhood\",\n      \"title\": \"Motherhood - Tips & Advice from Peanut\",\n      \"meta_description\": \"Everything you need to know about motherhood. Expert articles, development guides, parenting tips, and so much more.\"\n    },\n    {\n      \"id\": 55,\n      \"name\": \"Newborn\",\n      \"title\": null,\n      \"meta_description\": null\n    },\n    {\n      \"id\": 49,\n      \"name\": \"Parenthood\",\n      \"title\": null,\n      \"meta_description\": null\n    },\n    {\n      \"id\": 45,\n      \"name\": \"Parenting\",\n      \"title\": null,\n      \"meta_description\": null\n    },\n    {\n      \"id\": 5,\n      \"name\": \"Peanut News\",\n      \"title\": \"Peanut - App News & Updates\",\n      \"meta_description\": \"Everything you need to know about the Peanut app. Feature updates, app news, and handy how-tos.\"\n    },\n    {\n      \"id\": 61,\n      \"name\": \"Postpartum\",\n      \"title\": null,\n      \"meta_description\": null\n    },\n    {\n      \"id\": 2,\n      \"name\": \"Pregnancy\",\n      \"title\": \"Pregnancy - Tips & Advice from Peanut\",\n      \"meta_description\": \"Everything you need to know about pregnancy. Expert articles, week-by-week guides, baby name inspiration, and so much more. \"\n    },\n    {\n      \"id\": 57,\n      \"name\": \"Pregnancy Announcements\",\n      \"title\": null,\n      \"meta_description\": null\n    },\n    {\n      \"id\": 58,\n      \"name\": \"Pregnancy Care\",\n      \"title\": null,\n      \"meta_description\": null\n    },\n    {\n      \"id\": 54,\n      \"name\": \"Pregnancy Loss\",\n      \"title\": null,\n      \"meta_description\": null\n    },\n    {\n      \"id\": 78,\n      \"name\": \"Pregnancy nutrition\",\n      \"title\": null,\n      \"meta_description\": null\n    },\n    {\n      \"id\": 83,\n      \"name\": \"Pregnancy Nutrition\",\n      \"title\": null,\n      \"meta_description\": null\n    },\n    {\n      \"id\": 89,\n      \"name\": \"Pregnancy Scans\",\n      \"title\": null,\n      \"meta_description\": null\n    },\n    {\n      \"id\": 79,\n      \"name\": \"Pregnancy symptoms\",\n      \"title\": null,\n      \"meta_description\": null\n    },\n    {\n      \"id\": 64,\n      \"name\": \"Pregnancy Symptoms\",\n      \"title\": null,\n      \"meta_description\": null\n    },\n    {\n      \"id\": 74,\n      \"name\": \"Pregnancy tests\",\n      \"title\": null,\n      \"meta_description\": null\n    },\n    {\n      \"id\": 53,\n      \"name\": \"Pregnancy Tests\",\n      \"title\": null,\n      \"meta_description\": null\n    },\n    {\n      \"id\": 84,\n      \"name\": \"Pregnancy Week-by-Week\",\n      \"title\": null,\n      \"meta_description\": null\n    },\n    {\n      \"id\": 85,\n      \"name\": \"Pregnancy Weeky-by-Week\",\n      \"title\": null,\n      \"meta_description\": null\n    },\n    {\n      \"id\": 70,\n      \"name\": \"Pumping\",\n      \"title\": null,\n      \"meta_description\": null\n    },\n    {\n      \"id\": 88,\n      \"name\": \"Shopping\",\n      \"title\": null,\n      \"meta_description\": null\n    },\n    {\n      \"id\": 80,\n      \"name\": \"Teething\",\n      \"title\": null,\n      \"meta_description\": null\n    },\n    {\n      \"id\": 81,\n      \"name\": \"Toddler\",\n      \"title\": null,\n      \"meta_description\": null\n    },\n    {\n      \"id\": 71,\n      \"name\": \"Trying for a baby\",\n      \"title\": null,\n      \"meta_description\": null\n    },\n    {\n      \"id\": 10,\n      \"name\": \"Trying to conceive\",\n      \"title\": null,\n      \"meta_description\": null\n    },\n    {\n      \"id\": 51,\n      \"name\": \"Women's Health\",\n      \"title\": null,\n      \"meta_description\": null\n    },\n    {\n      \"id\": 91,\n      \"name\": \"Work & Motherhood\",\n      \"title\": null,\n      \"meta_description\": null\n    }\n  ]\n}",
          "latency": 0,
          "statusCode": 200,
          "label": "",
          "headers": [],
          "bodyType": "INLINE",
          "filePath": "",
          "databucketID": "",
          "sendFileAsBody": false,
          "rules": [
            {
              "target": "query",
              "modifier": "page",
              "value": "3",
              "invert": false,
              "operator": "equals"
            }
          ],
          "rulesOperator": "OR",
          "disableTemplating": false,
          "fallbackTo404": false,
          "default": false
        },
        {
          "uuid": "6f7f5e70-fdf2-4897-a68b-98a9be1ba8ee",
          "body": "{\n  \"pages\": [\n    {\n      \"published_at\": \"2023-06-13T15:31:00.000Z\",\n      \"heading\": \"Pregnancy Acne: Causes, Cures & What to Do\",\n      \"summary\": \"Hitting the spot.\",\n      \"slug\": \"blog/pregnancy-acne\",\n      \"locale\": \"en\",\n      \"children\": [],\n      \"featured\": false,\n      \"i18n_pages\": [\n        [\n          \"en\",\n          \"blog/pregnancy-acne\"\n        ]\n      ],\n      \"tag\": {\n        \"id\": 2,\n        \"name\": \"Pregnancy\"\n      },\n      \"hero_image_url\": \"https://assets-production.teampeanut.com/stored-image/{width}/2jws3-xaov5r.jpg?ow=1200&oh=700\",\n      \"author\": {\n        \"name\": \"Deborah Vieyra\",\n        \"avatar_url\": \"https://assets-production.teampeanut.com/stored-image/{width}/27l1n-s16i8q.jpg?ow=200&oh=200\"\n      }\n    },\n    {\n      \"published_at\": \"2023-06-13T15:23:00.000Z\",\n      \"heading\": \"Going Back to Work After Having a Baby: What To Know\",\n      \"summary\": \"It’s a challenge, but you can totally do it.\",\n      \"slug\": \"blog/going-back-to-work-after-baby\",\n      \"locale\": \"en\",\n      \"children\": [],\n      \"featured\": false,\n      \"i18n_pages\": [\n        [\n          \"en\",\n          \"blog/going-back-to-work-after-baby\"\n        ]\n      ],\n      \"tag\": {\n        \"id\": 91,\n        \"name\": \"Work & Motherhood\"\n      },\n      \"hero_image_url\": \"https://assets-production.teampeanut.com/stored-image/{width}/11ibv-m7osc5.jpg?ow=1200&oh=675\",\n      \"author\": {\n        \"name\": \"Tassia Agatowski\",\n        \"avatar_url\": \"https://assets-production.teampeanut.com/stored-image/{width}/11ibu-q7h4n7.jpg?ow=1781&oh=1780\"\n      }\n    },\n    {\n      \"published_at\": \"2023-06-13T15:05:00.000Z\",\n      \"heading\": \"Can You Swim On Your Period?\",\n      \"summary\": \"Let’s dive in. 🩸\",\n      \"slug\": \"blog/can-you-swim-on-your-period\",\n      \"locale\": \"en\",\n      \"children\": [],\n      \"featured\": false,\n      \"i18n_pages\": [\n        [\n          \"en\",\n          \"blog/can-you-swim-on-your-period\"\n        ]\n      ],\n      \"tag\": {\n        \"id\": 14,\n        \"name\": \"Lifestyle\"\n      },\n      \"hero_image_url\": \"https://assets-production.teampeanut.com/stored-image/{width}/1ys50-5lfqv6.jpg?ow=1200&oh=675\",\n      \"author\": {\n        \"name\": \"Peanut\",\n        \"avatar_url\": \"https://assets-production.teampeanut.com/stored-image/{width}/1ys4z-ovimw9.jpg?ow=1781&oh=1780\"\n      }\n    },\n    {\n      \"published_at\": \"2023-06-13T14:53:00.000Z\",\n      \"heading\": \"11 Hacks & Tips for Working Mums\",\n      \"summary\": \"Working 9 to 5… then 5 to 9.\",\n      \"slug\": \"blog/tips-for-working-mums\",\n      \"locale\": \"en\",\n      \"children\": [],\n      \"featured\": false,\n      \"i18n_pages\": [\n        [\n          \"en\",\n          \"blog/tips-for-working-mums\"\n        ]\n      ],\n      \"tag\": {\n        \"id\": 91,\n        \"name\": \"Work & Motherhood\"\n      },\n      \"hero_image_url\": \"https://assets-production.teampeanut.com/stored-image/{width}/1448p-3i4bsn.jpg?ow=1200&oh=675\",\n      \"author\": {\n        \"name\": \"Tassia Agatowski\",\n        \"avatar_url\": \"https://assets-production.teampeanut.com/stored-image/{width}/1448m-vssbs1.jpg?ow=1781&oh=1780\"\n      }\n    },\n    {\n      \"published_at\": \"2023-06-13T12:22:00.000Z\",\n      \"heading\": \"How To Be a Working Mum: 7 Hints & Tips\",\n      \"summary\": \"Working two jobs!\",\n      \"slug\": \"blog/how-to-be-a-working-mum\",\n      \"locale\": \"en\",\n      \"children\": [],\n      \"featured\": false,\n      \"i18n_pages\": [\n        [\n          \"en\",\n          \"blog/how-to-be-a-working-mum\"\n        ]\n      ],\n      \"tag\": {\n        \"id\": 91,\n        \"name\": \"Work & Motherhood\"\n      },\n      \"hero_image_url\": \"https://assets-production.teampeanut.com/stored-image/{width}/254x6-spjtwz.jpg?ow=1200&oh=600\",\n      \"author\": {\n        \"name\": \"Tassia Agatowski\",\n        \"avatar_url\": \"https://assets-production.teampeanut.com/stored-image/{width}/254x5-hoecji.jpg?ow=1781&oh=1780\"\n      }\n    },\n    {\n      \"published_at\": \"2023-06-13T10:16:00.000Z\",\n      \"heading\": \"62 Self-Care Ideas for Mums to Calm Your Mind\",\n      \"summary\": \"Your time is precious, so find what works for you!\",\n      \"slug\": \"blog/self-care-ideas-for-mums\",\n      \"locale\": \"en\",\n      \"children\": [],\n      \"featured\": false,\n      \"i18n_pages\": [\n        [\n          \"en\",\n          \"blog/self-care-ideas-for-mums\"\n        ]\n      ],\n      \"tag\": {\n        \"id\": 91,\n        \"name\": \"Work & Motherhood\"\n      },\n      \"hero_image_url\": \"https://assets-production.teampeanut.com/stored-image/{width}/12mr7-6kznzl.jpg?ow=1200&oh=675\",\n      \"author\": {\n        \"name\": \"Tassia Agatowski\",\n        \"avatar_url\": \"https://assets-production.teampeanut.com/stored-image/{width}/12mr5-yq2q2l.jpg?ow=1781&oh=1780\"\n      }\n    },\n    {\n      \"published_at\": \"2023-06-12T14:45:00.000Z\",\n      \"heading\": \"14 LGBTQIA+ Couples You Should Follow ASAP\",\n      \"summary\": \"Like, follow, subscribe. 🏳️‍🌈\",\n      \"slug\": \"blog/lgbtqia-couples-to-follow\",\n      \"locale\": \"en\",\n      \"children\": [],\n      \"featured\": false,\n      \"i18n_pages\": [\n        [\n          \"en\",\n          \"blog/lgbtqia-couples-to-follow\"\n        ]\n      ],\n      \"tag\": {\n        \"id\": 92,\n        \"name\": \"LGBTQIA+\"\n      },\n      \"hero_image_url\": \"https://assets-production.teampeanut.com/stored-image/{width}/2jts6-j3sgte.jpg?ow=1200&oh=452\",\n      \"author\": {\n        \"name\": \"Tassia Agatowski\",\n        \"avatar_url\": \"https://assets-production.teampeanut.com/stored-image/{width}/130tj-89szhb.jpg?ow=1781&oh=1780\"\n      }\n    },\n    {\n      \"published_at\": \"2023-06-12T12:05:00.000Z\",\n      \"heading\": \"Screen Time for Kids: What Parents Need to Know\",\n      \"summary\": \"Find the sweet spot for healthy development. \",\n      \"slug\": \"blog/screen-time-for-kids\",\n      \"locale\": \"en\",\n      \"children\": [],\n      \"featured\": false,\n      \"i18n_pages\": [\n        [\n          \"en\",\n          \"blog/screen-time-for-kids\"\n        ]\n      ],\n      \"tag\": {\n        \"id\": 3,\n        \"name\": \"Motherhood\"\n      },\n      \"hero_image_url\": \"https://assets-production.teampeanut.com/stored-image/{width}/2jtg0-9d0ysd.jpg?ow=1200&oh=700\",\n      \"author\": {\n        \"name\": \"Keshia Sophia Roelofs\"\n      }\n    },\n    {\n      \"published_at\": \"2023-06-09T14:26:00.000Z\",\n      \"heading\": \"Why Choose a Blood Pregnancy Test?\",\n      \"summary\": \"Spoiler alert: there are two types of blood pregnancy tests.\",\n      \"slug\": \"blog/blood-pregnancy-test\",\n      \"locale\": \"en\",\n      \"children\": [],\n      \"featured\": false,\n      \"i18n_pages\": [\n        [\n          \"es\",\n          \"blog/prueba-de-embarazo-de-sangre\"\n        ],\n        [\n          \"en\",\n          \"blog/blood-pregnancy-test\"\n        ]\n      ],\n      \"tag\": {\n        \"id\": 2,\n        \"name\": \"Pregnancy\"\n      },\n      \"hero_image_url\": \"https://assets-production.teampeanut.com/stored-image/{width}/2jmvk-gei0o3.jpg?ow=1200&oh=700\",\n      \"author\": {\n        \"name\": \"Peanut\",\n        \"avatar_url\": \"https://assets-production.teampeanut.com/stored-image/{width}/137st-chw6gj.jpg?ow=1781&oh=1780\"\n      }\n    },\n    {\n      \"published_at\": \"2023-06-09T14:01:00.000Z\",\n      \"heading\": \"13 Natural Ways to Induce Labor Naturally\",\n      \"summary\": \"So over being pregnant? We hear ya!\\n\",\n      \"slug\": \"blog/ways-to-induce-labor\",\n      \"locale\": \"en\",\n      \"children\": [],\n      \"featured\": false,\n      \"i18n_pages\": [\n        [\n          \"en\",\n          \"blog/ways-to-induce-labor\"\n        ]\n      ],\n      \"tag\": {\n        \"id\": 2,\n        \"name\": \"Pregnancy\"\n      },\n      \"hero_image_url\": \"https://assets-production.teampeanut.com/stored-image/{width}/2jmrf-jzqsti.jpg?ow=1200&oh=700\",\n      \"author\": {\n        \"name\": \"Keshia Sophia Roelofs\",\n        \"avatar_url\": \"https://assets-production.teampeanut.com/stored-image/{width}/18dgv-5zfs9p.jpg?ow=1781&oh=1780\"\n      }\n    },\n    {\n      \"published_at\": \"2023-06-09T13:18:00.000Z\",\n      \"heading\": \"How to Count Pregnancy Weeks\",\n      \"summary\": \"Get out your calendar. And maybe a calculator.\",\n      \"slug\": \"blog/how-to-count-pregnancy-weeks\",\n      \"locale\": \"en\",\n      \"children\": [],\n      \"featured\": false,\n      \"i18n_pages\": [\n        [\n          \"es\",\n          \"blog/como-cuentas-tus-semanas-de-embarazo\"\n        ],\n        [\n          \"en\",\n          \"blog/how-to-count-pregnancy-weeks\"\n        ]\n      ],\n      \"tag\": {\n        \"id\": 2,\n        \"name\": \"Pregnancy\"\n      },\n      \"hero_image_url\": \"https://assets-production.teampeanut.com/stored-image/{width}/2jmn6-i916pw.jpg?ow=1200&oh=700\",\n      \"author\": {\n        \"name\": \"Peanut\",\n        \"avatar_url\": \"https://assets-production.teampeanut.com/stored-image/{width}/14h93-rri07z.jpg?ow=1781&oh=1780\"\n      }\n    },\n    {\n      \"published_at\": \"2023-06-09T13:13:00.000Z\",\n      \"heading\": \"Can Birth Control Cause Infertility? The Whole Story\",\n      \"summary\": \"Good news here! 🎉\",\n      \"slug\": \"blog/can-birth-control-cause-infertility\",\n      \"locale\": \"en\",\n      \"children\": [],\n      \"featured\": false,\n      \"i18n_pages\": [\n        [\n          \"en\",\n          \"blog/can-birth-control-cause-infertility\"\n        ]\n      ],\n      \"tag\": {\n        \"id\": 37,\n        \"name\": \"Fertility\"\n      },\n      \"hero_image_url\": \"https://assets-production.teampeanut.com/stored-image/{width}/24o78-od40vj.jpg?ow=1200&oh=600\",\n      \"author\": {\n        \"name\": \"Cassidy Parker\",\n        \"avatar_url\": \"https://assets-production.teampeanut.com/stored-image/{width}/24o75-jkq4an.jpg?ow=1781&oh=1780\"\n      }\n    },\n    {\n      \"published_at\": \"2023-06-09T12:14:00.000Z\",\n      \"heading\": \"Vaginal Itching: Why is My Vagina Itchy?\",\n      \"summary\": \"Ditch that itch!\",\n      \"slug\": \"blog/vaginal-itching\",\n      \"locale\": \"en\",\n      \"children\": [],\n      \"featured\": false,\n      \"i18n_pages\": [\n        [\n          \"en\",\n          \"blog/vaginal-itching\"\n        ]\n      ],\n      \"tag\": {\n        \"id\": 14,\n        \"name\": \"Lifestyle\"\n      },\n      \"hero_image_url\": \"https://assets-production.teampeanut.com/stored-image/{width}/14jx1-wcv0yd.jpg?ow=1200&oh=675\",\n      \"author\": {\n        \"name\": \"Team Peanut\",\n        \"avatar_url\": \"https://assets-production.teampeanut.com/stored-image/{width}/14jwx-lw8ae.jpg?ow=1781&oh=1780\"\n      }\n    },\n    {\n      \"published_at\": \"2023-06-09T12:04:00.000Z\",\n      \"heading\": \"FSH Levels Through Menopause: A Helpful Chart\",\n      \"summary\": \"Going up? 📈\",\n      \"slug\": \"blog/fsh-levels-menopause-chart\",\n      \"locale\": \"en\",\n      \"children\": [],\n      \"featured\": false,\n      \"i18n_pages\": [\n        [\n          \"en\",\n          \"blog/fsh-levels-menopause-chart\"\n        ]\n      ],\n      \"tag\": {\n        \"id\": 23,\n        \"name\": \"Menopause\"\n      },\n      \"hero_image_url\": \"https://assets-production.teampeanut.com/stored-image/{width}/1zwlc-rluhbi.jpg?ow=1200&oh=675\",\n      \"author\": {\n        \"name\": \"Tassia Agatowski\",\n        \"avatar_url\": \"https://assets-production.teampeanut.com/stored-image/{width}/1zwlb-6pdnlu.jpg?ow=1781&oh=1780\"\n      }\n    }\n  ],\n  \"last_page\": false,\n  \"tags\": [\n    {\n      \"id\": 56,\n      \"name\": \"Baby\",\n      \"title\": null,\n      \"meta_description\": null\n    },\n    {\n      \"id\": 82,\n      \"name\": \"Baby care\",\n      \"title\": null,\n      \"meta_description\": null\n    },\n    {\n      \"id\": 73,\n      \"name\": \"Baby Care\",\n      \"title\": null,\n      \"meta_description\": null\n    },\n    {\n      \"id\": 63,\n      \"name\": \"Baby Feeding\",\n      \"title\": null,\n      \"meta_description\": null\n    },\n    {\n      \"id\": 77,\n      \"name\": \"Baby names\",\n      \"title\": null,\n      \"meta_description\": null\n    },\n    {\n      \"id\": 52,\n      \"name\": \"Baby Names\",\n      \"title\": null,\n      \"meta_description\": null\n    },\n    {\n      \"id\": 86,\n      \"name\": \"Baby Products\",\n      \"title\": null,\n      \"meta_description\": null\n    },\n    {\n      \"id\": 66,\n      \"name\": \"Baby Showers\",\n      \"title\": null,\n      \"meta_description\": null\n    },\n    {\n      \"id\": 72,\n      \"name\": \"Baby sleep\",\n      \"title\": null,\n      \"meta_description\": null\n    },\n    {\n      \"id\": 67,\n      \"name\": \"Baby Sleep\",\n      \"title\": null,\n      \"meta_description\": null\n    },\n    {\n      \"id\": 59,\n      \"name\": \"Beauty\",\n      \"title\": null,\n      \"meta_description\": null\n    },\n    {\n      \"id\": 69,\n      \"name\": \"Birth\",\n      \"title\": null,\n      \"meta_description\": null\n    },\n    {\n      \"id\": 62,\n      \"name\": \"Breastfeeding\",\n      \"title\": null,\n      \"meta_description\": null\n    },\n    {\n      \"id\": 43,\n      \"name\": \"Children's Activities\",\n      \"title\": null,\n      \"meta_description\": null\n    },\n    {\n      \"id\": 76,\n      \"name\": \"Family\",\n      \"title\": null,\n      \"meta_description\": null\n    },\n    {\n      \"id\": 37,\n      \"name\": \"Fertility\",\n      \"title\": null,\n      \"meta_description\": null\n    },\n    {\n      \"id\": 68,\n      \"name\": \"From Peanut\",\n      \"title\": null,\n      \"meta_description\": null\n    },\n    {\n      \"id\": 50,\n      \"name\": \"Labor\",\n      \"title\": null,\n      \"meta_description\": null\n    },\n    {\n      \"id\": 92,\n      \"name\": \"LGBTQIA+\",\n      \"title\": null,\n      \"meta_description\": null\n    },\n    {\n      \"id\": 14,\n      \"name\": \"Lifestyle\",\n      \"title\": null,\n      \"meta_description\": null\n    },\n    {\n      \"id\": 23,\n      \"name\": \"Menopause\",\n      \"title\": null,\n      \"meta_description\": null\n    },\n    {\n      \"id\": 75,\n      \"name\": \"Mental health\",\n      \"title\": null,\n      \"meta_description\": null\n    },\n    {\n      \"id\": 60,\n      \"name\": \"Mental Health\",\n      \"title\": null,\n      \"meta_description\": null\n    },\n    {\n      \"id\": 3,\n      \"name\": \"Motherhood\",\n      \"title\": \"Motherhood - Tips & Advice from Peanut\",\n      \"meta_description\": \"Everything you need to know about motherhood. Expert articles, development guides, parenting tips, and so much more.\"\n    },\n    {\n      \"id\": 55,\n      \"name\": \"Newborn\",\n      \"title\": null,\n      \"meta_description\": null\n    },\n    {\n      \"id\": 49,\n      \"name\": \"Parenthood\",\n      \"title\": null,\n      \"meta_description\": null\n    },\n    {\n      \"id\": 45,\n      \"name\": \"Parenting\",\n      \"title\": null,\n      \"meta_description\": null\n    },\n    {\n      \"id\": 5,\n      \"name\": \"Peanut News\",\n      \"title\": \"Peanut - App News & Updates\",\n      \"meta_description\": \"Everything you need to know about the Peanut app. Feature updates, app news, and handy how-tos.\"\n    },\n    {\n      \"id\": 61,\n      \"name\": \"Postpartum\",\n      \"title\": null,\n      \"meta_description\": null\n    },\n    {\n      \"id\": 2,\n      \"name\": \"Pregnancy\",\n      \"title\": \"Pregnancy - Tips & Advice from Peanut\",\n      \"meta_description\": \"Everything you need to know about pregnancy. Expert articles, week-by-week guides, baby name inspiration, and so much more. \"\n    },\n    {\n      \"id\": 57,\n      \"name\": \"Pregnancy Announcements\",\n      \"title\": null,\n      \"meta_description\": null\n    },\n    {\n      \"id\": 58,\n      \"name\": \"Pregnancy Care\",\n      \"title\": null,\n      \"meta_description\": null\n    },\n    {\n      \"id\": 54,\n      \"name\": \"Pregnancy Loss\",\n      \"title\": null,\n      \"meta_description\": null\n    },\n    {\n      \"id\": 78,\n      \"name\": \"Pregnancy nutrition\",\n      \"title\": null,\n      \"meta_description\": null\n    },\n    {\n      \"id\": 83,\n      \"name\": \"Pregnancy Nutrition\",\n      \"title\": null,\n      \"meta_description\": null\n    },\n    {\n      \"id\": 89,\n      \"name\": \"Pregnancy Scans\",\n      \"title\": null,\n      \"meta_description\": null\n    },\n    {\n      \"id\": 79,\n      \"name\": \"Pregnancy symptoms\",\n      \"title\": null,\n      \"meta_description\": null\n    },\n    {\n      \"id\": 64,\n      \"name\": \"Pregnancy Symptoms\",\n      \"title\": null,\n      \"meta_description\": null\n    },\n    {\n      \"id\": 74,\n      \"name\": \"Pregnancy tests\",\n      \"title\": null,\n      \"meta_description\": null\n    },\n    {\n      \"id\": 53,\n      \"name\": \"Pregnancy Tests\",\n      \"title\": null,\n      \"meta_description\": null\n    },\n    {\n      \"id\": 84,\n      \"name\": \"Pregnancy Week-by-Week\",\n      \"title\": null,\n      \"meta_description\": null\n    },\n    {\n      \"id\": 85,\n      \"name\": \"Pregnancy Weeky-by-Week\",\n      \"title\": null,\n      \"meta_description\": null\n    },\n    {\n      \"id\": 70,\n      \"name\": \"Pumping\",\n      \"title\": null,\n      \"meta_description\": null\n    },\n    {\n      \"id\": 88,\n      \"name\": \"Shopping\",\n      \"title\": null,\n      \"meta_description\": null\n    },\n    {\n      \"id\": 80,\n      \"name\": \"Teething\",\n      \"title\": null,\n      \"meta_description\": null\n    },\n    {\n      \"id\": 81,\n      \"name\": \"Toddler\",\n      \"title\": null,\n      \"meta_description\": null\n    },\n    {\n      \"id\": 71,\n      \"name\": \"Trying for a baby\",\n      \"title\": null,\n      \"meta_description\": null\n    },\n    {\n      \"id\": 10,\n      \"name\": \"Trying to conceive\",\n      \"title\": null,\n      \"meta_description\": null\n    },\n    {\n      \"id\": 51,\n      \"name\": \"Women's Health\",\n      \"title\": null,\n      \"meta_description\": null\n    },\n    {\n      \"id\": 91,\n      \"name\": \"Work & Motherhood\",\n      \"title\": null,\n      \"meta_description\": null\n    }\n  ]\n}",
          "latency": 0,
          "statusCode": 200,
          "label": "",
          "headers": [],
          "bodyType": "INLINE",
          "filePath": "",
          "databucketID": "",
          "sendFileAsBody": false,
          "rules": [
            {
              "target": "query",
              "modifier": "page",
              "value": "4",
              "invert": false,
              "operator": "equals"
            }
          ],
          "rulesOperator": "OR",
          "disableTemplating": false,
          "fallbackTo404": false,
          "default": false
        }
      ],
      "enabled": true,
      "responseMode": null
    }
  ],
  "proxyMode": false,
  "proxyHost": "",
  "proxyRemovePrefix": false,
  "tlsOptions": {
    "enabled": false,
    "type": "CERT",
    "pfxPath": "",
    "certPath": "",
    "keyPath": "",
    "caPath": "",
    "passphrase": ""
  },
  "cors": true,
  "headers": [
    {
      "key": "Content-Type",
      "value": "application/json"
    }
  ],
  "proxyReqHeaders": [
    {
      "key": "",
      "value": ""
    }
  ],
  "proxyResHeaders": [
    {
      "key": "",
      "value": ""
    }
  ],
  "data": []
}